[
  [
    {
      "img":"/image/M1.jpg",
      "tittle":"孕妇必备"
    },
    {
      "img":"/image/M2.jpg",
      "tittle":"准爸必备"
    },
    {
      "img":"/image/M3.jpg",
      "tittle":"婴儿奶粉"
    },
    {
      "img":"/image/M4.jpg",
      "tittle":"婴幼保健"
    },
    {
      "img":"/image/M5.jpg",
      "tittle":"宝宝服饰"
    },
    {
      "img":"/image/M6.jpg",
      "tittle":"婴幼玩具"
    },
    {
      "img":"/image/M7.jpg",
      "tittle":"婴儿洗护"
    },
    {
      "img":"/image/M8.jpg",
      "tittle":"宝宝专场"
    },
    {
      "img":"/image/L4.jpg",
      "tittle":"热门新品"
    }
  ],
  [
    {
      "img":"/image/H1.jpg",
      "tittle":"助睡眠"
    },{
      "img":"/image/H2.jpg",
      "tittle":"抗氧化"
    },
    {
      "img":"/image/H3.jpg",
      "tittle":"维生素"
    },
    {
      "img":"/image/H4.jpg",
      "tittle":"减肥瘦身"
    },
    {
      "img":"/image/H5.jpg",
      "tittle":"健身必备"
    },
    {
      "img":"/image/H6.jpg",
      "tittle":"排毒养颜"
    },
    {
      "img":"/image/H7.jpg",
      "tittle":"健骨补钙"
    },
    {
      "img":"/image/H8.jpg",
      "tittle":"血糖平衡"
    },
    {
      "img":"/image/H9.jpg",
      "tittle":"护心健脑"
    },
    {
      "img":"/image/H10.jpg",
      "tittle":"男性健康"
    },
    {
      "img":"/image/H11.jpg",
      "tittle":"女性健康"
    },
    {
      "img":"/image/L4.jpg",
      "tittle":"热门新品"
    }
  ],
  [
    {
      "img":"/image/B1.jpg",
      "tittle":"面部保养"
    },
    {
      "img":"/image/B2.jpg",
      "tittle":"身体保养"
    },
    {
      "img":"/image/B3.jpg",
      "tittle":"面膜"
    },
    {
      "img":"/image/B4.jpg",
      "tittle":"彩妆"
    },
    {
      "img":"/image/B5.jpg",
      "tittle":"美容工具"
    },
    {
      "img":"/image/B6.jpg",
      "tittle":"个人护理"
    },
    {
      "img":"/image/B7.jpg",
      "tittle":"头发洗护"
    },
    {
      "img":"/image/B8.jpg",
      "tittle":"闺蜜的秘密"
    },
    {
      "img":"/image/L4.jpg",
      "tittle":"热门新品"
    }
  ],
  [
    {
      "img":"/image/G1.jpg",
      "tittle":"零食"
    },
    {
      "img":"/image/G2.jpg",
      "tittle":"代餐"
    },
    {
      "img":"/image/G3.jpg",
      "tittle":"营养食品"
    },
    {
      "img":"/image/G4.jpg",
      "tittle":"纤维素"
    },
    {
      "img":"/image/G5.jpg",
      "tittle":"有机食品"
    },
    {
      "img":"/image/G6.jpg",
      "tittle":"奶制品"
    }
  ],
  [
    {
      "img":"/image/L1.jpg",
      "tittle":"厨房用品"
    },
    {
      "img":"/image/L2.jpg",
      "tittle":"床上用品"
    },
    {
      "img":"/image/L4.jpg",
      "tittle":"热门新品"
    }
  ],
  [
    {
      "img":"/image/L3.jpg",
      "tittle":"服饰鞋帽"
    },
    {
      "img":"/image/L4.jpg",
      "tittle":"热门新品"
    },
    {
      "img":"/image/L4.jpg",
      "tittle":"热门新品"
    }
  ]
]
